{"新北市板橋區":{"臺北市":{"male":137,"female":149},"新北市":{"male":0,"female":0},"桃園市":{"male":77,"female":84},"臺中市":{"male":29,"female":29},"臺南市":{"male":13,"female":12},"高雄市":{"male":15,"female":19}},"新北市三重區":{"臺北市":{"male":134,"female":176},"新北市":{"male":0,"female":0},"桃園市":{"male":49,"female":63},"臺中市":{"male":15,"female":17},"臺南市":{"male":8,"female":6},"高雄市":{"male":17,"female":10}},"新北市中和區":{"臺北市":{"male":107,"female":140},"新北市":{"male":0,"female":0},"桃園市":{"male":52,"female":58},"臺中市":{"male":20,"female":30},"臺南市":{"male":8,"female":12},"高雄市":{"male":13,"female":9}},"新北市永和區":{"臺北市":{"male":80,"female":70},"新北市":{"male":0,"female":0},"桃園市":{"male":27,"female":24},"臺中市":{"male":8,"female":4},"臺南市":{"male":5,"female":7},"高雄市":{"male":6,"female":6}},"新北市新莊區":{"臺北市":{"male":57,"female":69},"新北市":{"male":0,"female":0},"桃園市":{"male":82,"female":111},"臺中市":{"male":12,"female":16},"臺南市":{"male":6,"female":7},"高雄市":{"male":11,"female":18}},"新北市新店區":{"臺北市":{"male":155,"female":153},"新北市":{"male":0,"female":0},"桃園市":{"male":36,"female":51},"臺中市":{"male":21,"female":27},"臺南市":{"male":11,"female":5},"高雄市":{"male":16,"female":12}},"新北市樹林區":{"臺北市":{"male":31,"female":30},"新北市":{"male":0,"female":0},"桃園市":{"male":65,"female":51},"臺中市":{"male":3,"female":4},"臺南市":{"male":3,"female":2},"高雄市":{"male":6,"female":2}},"新北市鶯歌區":{"臺北市":{"male":7,"female":14},"新北市":{"male":0,"female":0},"桃園市":{"male":62,"female":77},"臺中市":{"male":4,"female":3},"臺南市":{"male":2,"female":6},"高雄市":{"male":2,"female":1}},"新北市三峽區":{"臺北市":{"male":18,"female":12},"新北市":{"male":0,"female":0},"桃園市":{"male":29,"female":32},"臺中市":{"male":2,"female":3},"臺南市":{"male":1,"female":2},"高雄市":{"male":2,"female":2}},"新北市淡水區":{"臺北市":{"male":65,"female":88},"新北市":{"male":0,"female":0},"桃園市":{"male":17,"female":16},"臺中市":{"male":11,"female":12},"臺南市":{"male":5,"female":7},"高雄市":{"male":6,"female":6}},"新北市汐止區":{"臺北市":{"male":121,"female":103},"新北市":{"male":0,"female":0},"桃園市":{"male":21,"female":25},"臺中市":{"male":10,"female":12},"臺南市":{"male":4,"female":3},"高雄市":{"male":3,"female":2}},"新北市瑞芳區":{"臺北市":{"male":6,"female":6},"新北市":{"male":0,"female":0},"桃園市":{"male":4,"female":8},"臺中市":{"male":1,"female":2},"臺南市":{"male":0,"female":1},"高雄市":{"male":0,"female":0}},"新北市土城區":{"臺北市":{"male":31,"female":48},"新北市":{"male":0,"female":0},"桃園市":{"male":37,"female":52},"臺中市":{"male":8,"female":13},"臺南市":{"male":9,"female":5},"高雄市":{"male":7,"female":10}},"新北市蘆洲區":{"臺北市":{"male":42,"female":63},"新北市":{"male":0,"female":0},"桃園市":{"male":20,"female":29},"臺中市":{"male":2,"female":2},"臺南市":{"male":8,"female":4},"高雄市":{"male":6,"female":1}},"新北市五股區":{"臺北市":{"male":19,"female":23},"新北市":{"male":0,"female":0},"桃園市":{"male":6,"female":14},"臺中市":{"male":7,"female":8},"臺南市":{"male":2,"female":2},"高雄市":{"male":2,"female":0}},"新北市泰山區":{"臺北市":{"male":13,"female":13},"新北市":{"male":0,"female":0},"桃園市":{"male":9,"female":18},"臺中市":{"male":2,"female":3},"臺南市":{"male":1,"female":0},"高雄市":{"male":2,"female":3}},"新北市林口區":{"臺北市":{"male":23,"female":16},"新北市":{"male":0,"female":0},"桃園市":{"male":55,"female":61},"臺中市":{"male":2,"female":7},"臺南市":{"male":1,"female":4},"高雄市":{"male":4,"female":4}},"新北市深坑區":{"臺北市":{"male":16,"female":27},"新北市":{"male":0,"female":0},"桃園市":{"male":6,"female":4},"臺中市":{"male":2,"female":3},"臺南市":{"male":0,"female":0},"高雄市":{"male":1,"female":0}},"新北市石碇區":{"臺北市":{"male":2,"female":1},"新北市":{"male":0,"female":0},"桃園市":{"male":0,"female":1},"臺中市":{"male":1,"female":1},"臺南市":{"male":0,"female":0},"高雄市":{"male":0,"female":0}},"新北市坪林區":{"臺北市":{"male":1,"female":3},"新北市":{"male":0,"female":0},"桃園市":{"male":1,"female":1},"臺中市":{"male":0,"female":0},"臺南市":{"male":0,"female":0},"高雄市":{"male":0,"female":0}},"新北市三芝區":{"臺北市":{"male":7,"female":5},"新北市":{"male":0,"female":0},"桃園市":{"male":2,"female":1},"臺中市":{"male":0,"female":2},"臺南市":{"male":0,"female":1},"高雄市":{"male":1,"female":2}},"新北市石門區":{"臺北市":{"male":1,"female":5},"新北市":{"male":0,"female":0},"桃園市":{"male":1,"female":4},"臺中市":{"male":0,"female":0},"臺南市":{"male":0,"female":0},"高雄市":{"male":0,"female":1}},"新北市八里區":{"臺北市":{"male":10,"female":17},"新北市":{"male":0,"female":0},"桃園市":{"male":7,"female":5},"臺中市":{"male":1,"female":4},"臺南市":{"male":0,"female":0},"高雄市":{"male":1,"female":2}},"新北市平溪區":{"臺北市":{"male":3,"female":2},"新北市":{"male":0,"female":0},"桃園市":{"male":2,"female":3},"臺中市":{"male":0,"female":0},"臺南市":{"male":0,"female":0},"高雄市":{"male":1,"female":1}},"新北市雙溪區":{"臺北市":{"male":1,"female":0},"新北市":{"male":0,"female":0},"桃園市":{"male":2,"female":1},"臺中市":{"male":1,"female":0},"臺南市":{"male":0,"female":0},"高雄市":{"male":0,"female":1}},"新北市貢寮區":{"臺北市":{"male":0,"female":1},"新北市":{"male":0,"female":0},"桃園市":{"male":2,"female":1},"臺中市":{"male":1,"female":0},"臺南市":{"male":0,"female":0},"高雄市":{"male":0,"female":0}},"新北市金山區":{"臺北市":{"male":4,"female":6},"新北市":{"male":0,"female":0},"桃園市":{"male":2,"female":2},"臺中市":{"male":0,"female":0},"臺南市":{"male":0,"female":1},"高雄市":{"male":0,"female":0}},"新北市萬里區":{"臺北市":{"male":1,"female":8},"新北市":{"male":0,"female":0},"桃園市":{"male":1,"female":1},"臺中市":{"male":1,"female":0},"臺南市":{"male":0,"female":1},"高雄市":{"male":1,"female":2}},"新北市烏來區":{"臺北市":{"male":0,"female":0},"新北市":{"male":0,"female":0},"桃園市":{"male":1,"female":0},"臺中市":{"male":0,"female":0},"臺南市":{"male":1,"female":0},"高雄市":{"male":0,"female":0}},"臺北市松山區":{"臺北市":{"male":0,"female":0},"新北市":{"male":86,"female":103},"桃園市":{"male":13,"female":14},"臺中市":{"male":4,"female":13},"臺南市":{"male":2,"female":2},"高雄市":{"male":2,"female":7}},"臺北市信義區":{"臺北市":{"male":0,"female":0},"新北市":{"male":97,"female":98},"桃園市":{"male":22,"female":26},"臺中市":{"male":6,"female":11},"臺南市":{"male":5,"female":9},"高雄市":{"male":4,"female":9}},"臺北市大安區":{"臺北市":{"male":0,"female":0},"新北市":{"male":138,"female":165},"桃園市":{"male":29,"female":30},"臺中市":{"male":13,"female":23},"臺南市":{"male":8,"female":8},"高雄市":{"male":4,"female":11}},"臺北市中山區":{"臺北市":{"male":0,"female":0},"新北市":{"male":105,"female":140},"桃園市":{"male":31,"female":29},"臺中市":{"male":13,"female":14},"臺南市":{"male":3,"female":2},"高雄市":{"male":9,"female":11}},"臺北市中正區":{"臺北市":{"male":0,"female":0},"新北市":{"male":119,"female":126},"桃園市":{"male":12,"female":11},"臺中市":{"male":12,"female":10},"臺南市":{"male":5,"female":7},"高雄市":{"male":7,"female":5}},"臺北市大同區":{"臺北市":{"male":0,"female":0},"新北市":{"male":79,"female":106},"桃園市":{"male":12,"female":17},"臺中市":{"male":4,"female":5},"臺南市":{"male":4,"female":2},"高雄市":{"male":1,"female":2}},"臺北市萬華區":{"臺北市":{"male":0,"female":0},"新北市":{"male":135,"female":131},"桃園市":{"male":19,"female":29},"臺中市":{"male":4,"female":8},"臺南市":{"male":11,"female":1},"高雄市":{"male":4,"female":3}},"臺北市文山區":{"臺北市":{"male":0,"female":0},"新北市":{"male":136,"female":181},"桃園市":{"male":38,"female":34},"臺中市":{"male":8,"female":18},"臺南市":{"male":9,"female":9},"高雄市":{"male":7,"female":13}},"臺北市南港區":{"臺北市":{"male":0,"female":0},"新北市":{"male":74,"female":71},"桃園市":{"male":10,"female":15},"臺中市":{"male":6,"female":4},"臺南市":{"male":1,"female":3},"高雄市":{"male":4,"female":2}},"臺北市內湖區":{"臺北市":{"male":0,"female":0},"新北市":{"male":139,"female":152},"桃園市":{"male":32,"female":31},"臺中市":{"male":18,"female":15},"臺南市":{"male":4,"female":6},"高雄市":{"male":10,"female":13}},"臺北市士林區":{"臺北市":{"male":0,"female":0},"新北市":{"male":110,"female":137},"桃園市":{"male":28,"female":33},"臺中市":{"male":12,"female":13},"臺南市":{"male":6,"female":9},"高雄市":{"male":4,"female":5}},"臺北市北投區":{"臺北市":{"male":0,"female":0},"新北市":{"male":158,"female":150},"桃園市":{"male":27,"female":32},"臺中市":{"male":9,"female":6},"臺南市":{"male":5,"female":1},"高雄市":{"male":9,"female":9}},"桃園市桃園區":{"臺北市":{"male":43,"female":51},"新北市":{"male":63,"female":87},"桃園市":{"male":0,"female":0},"臺中市":{"male":18,"female":25},"臺南市":{"male":7,"female":9},"高雄市":{"male":18,"female":8}},"桃園市中壢區":{"臺北市":{"male":17,"female":27},"新北市":{"male":44,"female":48},"桃園市":{"male":0,"female":0},"臺中市":{"male":6,"female":13},"臺南市":{"male":3,"female":9},"高雄市":{"male":7,"female":14}},"桃園市大溪區":{"臺北市":{"male":3,"female":12},"新北市":{"male":13,"female":16},"桃園市":{"male":0,"female":0},"臺中市":{"male":3,"female":1},"臺南市":{"male":0,"female":0},"高雄市":{"male":0,"female":0}},"桃園市楊梅區":{"臺北市":{"male":9,"female":11},"新北市":{"male":11,"female":15},"桃園市":{"male":0,"female":0},"臺中市":{"male":7,"female":7},"臺南市":{"male":4,"female":6},"高雄市":{"male":1,"female":4}},"桃園市蘆竹區":{"臺北市":{"male":13,"female":13},"新北市":{"male":30,"female":25},"桃園市":{"male":0,"female":0},"臺中市":{"male":4,"female":2},"臺南市":{"male":1,"female":5},"高雄市":{"male":2,"female":2}},"桃園市大園區":{"臺北市":{"male":8,"female":9},"新北市":{"male":10,"female":10},"桃園市":{"male":0,"female":0},"臺中市":{"male":3,"female":6},"臺南市":{"male":0,"female":3},"高雄市":{"male":3,"female":2}},"桃園市龜山區":{"臺北市":{"male":25,"female":26},"新北市":{"male":81,"female":62},"桃園市":{"male":0,"female":0},"臺中市":{"male":4,"female":9},"臺南市":{"male":3,"female":4},"高雄市":{"male":2,"female":3}},"桃園市八德區":{"臺北市":{"male":12,"female":16},"新北市":{"male":30,"female":36},"桃園市":{"male":0,"female":0},"臺中市":{"male":4,"female":12},"臺南市":{"male":4,"female":0},"高雄市":{"male":6,"female":5}},"桃園市龍潭區":{"臺北市":{"male":8,"female":9},"新北市":{"male":17,"female":19},"桃園市":{"male":0,"female":0},"臺中市":{"male":3,"female":8},"臺南市":{"male":0,"female":0},"高雄市":{"male":3,"female":0}},"桃園市平鎮區":{"臺北市":{"male":6,"female":19},"新北市":{"male":15,"female":17},"桃園市":{"male":0,"female":0},"臺中市":{"male":6,"female":13},"臺南市":{"male":4,"female":3},"高雄市":{"male":2,"female":4}},"桃園市新屋區":{"臺北市":{"male":2,"female":1},"新北市":{"male":3,"female":1},"桃園市":{"male":0,"female":0},"臺中市":{"male":3,"female":2},"臺南市":{"male":0,"female":0},"高雄市":{"male":0,"female":2}},"桃園市觀音區":{"臺北市":{"male":1,"female":0},"新北市":{"male":6,"female":7},"桃園市":{"male":0,"female":0},"臺中市":{"male":1,"female":1},"臺南市":{"male":0,"female":1},"高雄市":{"male":0,"female":0}},"桃園市復興區":{"臺北市":{"male":0,"female":2},"新北市":{"male":1,"female":1},"桃園市":{"male":0,"female":0},"臺中市":{"male":0,"female":0},"臺南市":{"male":0,"female":0},"高雄市":{"male":0,"female":0}},"臺中市中區":{"臺北市":{"male":2,"female":0},"新北市":{"male":0,"female":2},"桃園市":{"male":0,"female":2},"臺中市":{"male":0,"female":0},"臺南市":{"male":1,"female":0},"高雄市":{"male":0,"female":0}},"臺中市東區":{"臺北市":{"male":1,"female":2},"新北市":{"male":0,"female":3},"桃園市":{"male":2,"female":2},"臺中市":{"male":0,"female":0},"臺南市":{"male":0,"female":1},"高雄市":{"male":1,"female":4}}}